LICENSE.txt
MANIFEST.in
README.md
requirements.txt
setup.cfg
setup.py
awssearch/__init__.py
awssearch/__main__.py
awssearch/config.py
awssearch/output.py
awssearch/sh.py
awssearch.egg-info/PKG-INFO
awssearch.egg-info/SOURCES.txt
awssearch.egg-info/dependency_links.txt
awssearch.egg-info/entry_points.txt
awssearch.egg-info/requires.txt
awssearch.egg-info/top_level.txt
awssearch/cli/__init__.py
awssearch/cli/cli.py
awssearch/cli/ip/__init__.py
awssearch/cli/ip/ip.py